ak_selenium/__init__.py
ak_selenium/browser.py
ak_selenium/chrome.py
ak_selenium/firefox.py
ak_selenium/helium_attribs.py
ak_selenium-0.1.8.dist-info/LICENSE
ak_selenium-0.1.8.dist-info/WHEEL
ak_selenium-0.1.8.dist-info/METADATA
ak_selenium-0.1.8.dist-info/RECORD
