Metadata-Version: 2.1
Name: ak_selenium
Version: 0.1.8
Summary: Selenium package with requests integration and anti-bot detection measures
Author-email: Arun Kishore <pypi@rpakishore.co.in>
Requires-Python: >=3.11.0
Classifier: License :: OSI Approved :: MIT License
Requires-Dist: selenium
Requires-Dist: webdriver-manager>=3.9.1
Requires-Dist: ak_requests == 0.1.0
Requires-Dist: helium == 4.0.0
Requires-Dist: pytest ; extra == "test"
Requires-Dist: ipykernel ; extra == "test"
Project-URL: Home, https://github.com/rpakishore/ak_selenium
Provides-Extra: test
